stepchain/__init__.py
stepchain/exceptions.py
stepchain/py.typed
stepchain/chain/__init__.py
stepchain/chain/async_chain.py
stepchain/chain/chain.py
stepchain/chain/context.py
stepchain/chain/formatting.py
stepchain/chain/logging_setup.py
stepchain/chain/step.py
py_stepchain-0.1.2.dist-info/METADATA
py_stepchain-0.1.2.dist-info/WHEEL
py_stepchain-0.1.2.dist-info/licenses/LICENSE
py_stepchain-0.1.2.dist-info/RECORD
