Metadata-Version: 2.4
Name: py-stepchain
Version: 0.1.2
Summary: Composable chain-of-steps orchestrator with context passing, logging, retries, and validation.
Project-URL: Homepage, https://github.com/inderdevbhumi82-prog/stepchain
Project-URL: Issues, https://github.com/inderdevbhumi82-prog/stepchain/issues
Author: inderdevbhumi82-prog
License: MIT
License-File: LICENSE
Keywords: chain,contextmanager,orchestration,pipeline,steps
Classifier: Programming Language :: Python :: 3.10
Classifier: Programming Language :: Python :: 3.11
Classifier: Programming Language :: Python :: 3.12
Requires-Python: >=3.10
Provides-Extra: dev
Requires-Dist: black==24.8.0; extra == 'dev'
Requires-Dist: fastapi[standard]; extra == 'dev'
Requires-Dist: mypy==1.11.2; extra == 'dev'
Requires-Dist: pytest-asyncio; extra == 'dev'
Requires-Dist: pytest-cov==6.0.0; extra == 'dev'
Requires-Dist: pytest==8.3.3; extra == 'dev'
Requires-Dist: ruff; extra == 'dev'
Provides-Extra: docs
Requires-Dist: mike; extra == 'docs'
Requires-Dist: mkdocs; extra == 'docs'
Requires-Dist: mkdocs-include-markdown-plugin; extra == 'docs'
Requires-Dist: mkdocs-material; extra == 'docs'
Requires-Dist: mkdocstrings[python]; extra == 'docs'
Requires-Dist: pymdown-extensions; extra == 'docs'
